keMath/__init__.py
keMath/demo01.py
keMath/demo02.py
fuzhou_ke-0.0.1.dist-info/LICENSE
fuzhou_ke-0.0.1.dist-info/METADATA
fuzhou_ke-0.0.1.dist-info/WHEEL
fuzhou_ke-0.0.1.dist-info/top_level.txt
fuzhou_ke-0.0.1.dist-info/RECORD
