Metadata-Version: 2.1
Name: fuzhou-ke
Version: 0.0.1
Summary: 第一个py测试包
Home-page: https://github.com/pypa/sampleproject
Author: 福州柯先生
Author-email: ketianlin110@163.com
License: UNKNOWN
Platform: UNKNOWN
Classifier: Programming Language :: Python :: 3
Classifier: License :: OSI Approved :: MIT License
Classifier: Operating System :: OS Independent
License-File: LICENSE
